<?xml version="1.0" encoding="UTF-8"?>
<actions>
<action>
	<icon>utilities-terminal</icon>
	<name>Open Terminal Here</name>
	<submenu></submenu>
	<unique-id>1707300367029740-1</unique-id>
	<command>kitty %f</command>
	<description>Example for a custom action</description>
	<range></range>
	<patterns>*</patterns>
	<startup-notify/>
	<directories/>
</action>
<action>
	<icon>vscodium</icon>
	<name>Open in VSCodium</name>
	<submenu></submenu>
	<unique-id>1715062798706989-1</unique-id>
	<command>/usr/bin/codium --enable-features=UseOzonePlatform,WaylandWindowDecorations --ozone-platform=wayland %F</command>
	<description>Opens the current folder in VSCodium</description>
	<range>*</range>
	<patterns>*</patterns>
	<directories/>
</action>
</actions>
